mletrics/__init__.py
mletrics/_modidx.py
mletrics/classification.py
mletrics/stability.py
mletrics-0.0.3.dist-info/LICENSE
mletrics-0.0.3.dist-info/METADATA
mletrics-0.0.3.dist-info/WHEEL
mletrics-0.0.3.dist-info/entry_points.txt
mletrics-0.0.3.dist-info/top_level.txt
mletrics-0.0.3.dist-info/RECORD
