Metadata-Version: 2.1
Name: mletrics
Version: 0.0.3
Summary: Machine learning metrics that are not easy to found
Home-page: https://github.com/joaopcnogueira/mletrics/
Author: João Nogueira
Author-email: joao.nogueira@datarisk.io
License: Apache Software License 2.0
Keywords: nbdev
Platform: UNKNOWN
Classifier: Development Status :: 3 - Alpha
Classifier: Intended Audience :: Developers
Classifier: Natural Language :: English
Classifier: Programming Language :: Python :: 3.7
Classifier: Programming Language :: Python :: 3.8
Classifier: Programming Language :: Python :: 3.9
Classifier: Programming Language :: Python :: 3.10
Classifier: License :: OSI Approved :: Apache Software License
Requires-Python: >=3.7
License-File: LICENSE
Requires-Dist: fastcore
Requires-Dist: pandas
Requires-Dist: scikit-learn
Requires-Dist: scikit-plot
Provides-Extra: dev
